menuchoice/__init__.py
menuchoice/_validator.py
menuchoice/exceptions.py
menuchoice/cursor_control/_cursorInput.py
menuchoice/cursor_control/_textHandler.py
menuchoice-0.11.dist-info/METADATA
menuchoice-0.11.dist-info/WHEEL
menuchoice-0.11.dist-info/top_level.txt
menuchoice-0.11.dist-info/RECORD
