Metadata-Version: 2.1
Name: menuchoice
Version: 0.11
Summary: A terminal-based interactive menu selector which is controlled via arrow keys.
Home-page: https://github.com/xyzpw/menuchoice/
Author: xyzpw
Maintainer: xyzpw
License: MIT
Keywords: menu selector,item selector,ansi
Classifier: Programming Language :: Python :: 3
Classifier: Programming Language :: Python :: 3.8
Classifier: Programming Language :: Python :: 3.9
Classifier: Programming Language :: Python :: 3.10
Classifier: Programming Language :: Python :: 3.11
Classifier: Programming Language :: Python :: 3.12
Classifier: License :: OSI Approved :: MIT License
Classifier: Operating System :: POSIX :: Linux
Classifier: Environment :: Console
Classifier: Environment :: Console :: Curses
Classifier: Intended Audience :: Developers
